mailmerge.py
docx_mailmerge_hxd-0.6.2.dist-info/LICENSE.txt
docx_mailmerge_hxd-0.6.2.dist-info/METADATA
docx_mailmerge_hxd-0.6.2.dist-info/WHEEL
docx_mailmerge_hxd-0.6.2.dist-info/top_level.txt
docx_mailmerge_hxd-0.6.2.dist-info/RECORD
