Metadata-Version: 2.1
Name: docx-mailmerge-hxd
Version: 0.6.2
Summary: Performs a Mail Merge on docx (Microsoft Office Word) files
Home-page: http://github.com/ddonng/docx-mailmerge
Author: Bouke Haarsma
Author-email: bouke@haarsma.eu
License: MIT
Platform: UNKNOWN
Classifier: License :: OSI Approved :: MIT License
Classifier: Programming Language :: Python :: 2.7
Classifier: Programming Language :: Python :: 3.5
Classifier: Programming Language :: Python :: 3.6
Classifier: Programming Language :: Python :: 3.7
Classifier: Topic :: Text Processing
Requires-Dist: lxml
